<?xml version="1.0" encoding="UTF-8"?>
<persistence version="2.1" xmlns="http://xmlns.jcp.org/xml/ns/persistence" xmlns:xsi="http://www.w3.org/2001/XMLSchema-instance" xsi:schemaLocation="http://xmlns.jcp.org/xml/ns/persistence http://xmlns.jcp.org/xml/ns/persistence/persistence_2_1.xsd">
	<persistence-unit name="SHOPPING_ORM" transaction-type="RESOURCE_LOCAL">
		<provider>org.hibernate.ejb.HibernatePersistence</provider>
		<class>com.shopping.Attr</class>
		<class>com.shopping.Brand</class>
		<class>com.shopping.Cate</class>
		<class>com.shopping.CateAttrSet</class>
		<class>com.shopping.CateCate</class>
		<class>com.shopping.Consumer</class>
		<class>com.shopping.Merchant</class>
		<class>com.shopping.Order</class>
		<class>com.shopping.OrderDetail</class>
		<class>com.shopping.Prod</class>
		<class>com.shopping.ProdAttr</class>
		<class>com.shopping.User</class>
		<class>com.shopping.UserAuth</class>
		<properties>
			<property name="javax.persistence.jdbc.url" value="jdbc:mysql://localhost:3306/shdb"/>
			<property name="javax.persistence.jdbc.user" value="root"/>
			<property name="javax.persistence.jdbc.password" value="password"/>
			<property name="javax.persistence.jdbc.driver" value="com.mysql.jdbc.Driver"/>
		</properties>
	</persistence-unit>
</persistence>
